<?xml version="1.0"?><collection	xmlns="http://www-users.york.ac.uk/~rjm529/schema.xsd" xmlns:xs="http://www.w3.org/2001/XMLSchema"><slideshow><documentinfo>		<author>D6 Digital</author>		<version>1.0</version>		<title>GM Reference Tables</title>		<comment>Reference tables for the GM to use during play</comment>		<width>720</width>		<height>640</height>	</documentinfo>	<defaults>		<backgroundcolour>#FFFFFF</backgroundcolour>		<font>Times New Roman</font>		<fontsize>24</fontsize>		<fontcolour>#000000</fontcolour>		<linecolour>#000000</linecolour>		<fillcolour>#000000</fillcolour>	</defaults>	<slide id="1" duration="59" lastSlide="false">		<text font="Arial" fontsize="36" fontcolour="#000000" starttime="0"			layer="1" xstart="10" ystart="10" xend="110" yend="30">			<textbody bold="true" italic="false" underlined="true"				branch="0"><textstring>Character creation</textstring></textbody>		</text>		<text font="Arial" fontsize="24" fontcolour="#000000" starttime="0"			layer="1" xstart="10" ystart="40" xend="110" yend="400">			<textbody bold="true" italic="false" underlined="true"				branch="0"><textstring>Summary \n</textstring></textbody>
			<textbody bold="false" italic="true" underlined="false" branch="0">
				<textstring>1) Define Character Concept \n</textstring></textbody>
			<textbody bold="false" italic="true" underlined="false" branch="0">
				<textstring>2) Choose Background \n</textstring></textbody>
			<textbody bold="false" italic="true" underlined="false" branch="0">
				<textstring>3) Choose Faction \n</textstring>
			</textbody>
			<textbody bold="false" italic="true" underlined="false" branch="0">
				<textstring>4) Spend Free Points: \n a) 105 Aptitude points \n b) 1 Moxie \n c) 5,000 Credits \n d) 50 Rep \n e) Native Tongue \n</textstring></textbody>
			<textbody bold="false" italic="true" underlined="false" branch="0">
				<textstring>5) Spend Customisation Points: \n a) 1,000 CP to spend \n 15 CP = 1 Moxie \n 10 CP = 1 Aptitude point \n 5 CP = 1 Psi sleight \n 5 CP = 1 Specialisation \n 1 CP = 1 Skill point (up to 60) \n 2 CP = 1 Skill point (61-80) \n 1 CP = 1,000 Credits \n 1 CP = 10 Rep \n b) Active skill minimum: 400 CP \n c) Knowledge skill minimum: 300 CP \n d) Choose starting Morph \n e) Choose Traits \n</textstring></textbody>
			<textbody bold="false" italic="true" underlined="false" branch="0">
				<textstring>6) Purchase Gear</textstring></textbody>
			<textbody bold="false" italic="true" underlined="false" branch="0">
				<textstring>7) Choose Motivation</textstring></textbody>
			<textbody bold="false" italic="true" underlined="false" branch="0">
				<textstring>8) Calculate Remaining Stats</textstring></textbody>
			<textbody bold="false" italic="true" underlined="false" branch="0">
				<textstring>9) Detail the Character</textstring></textbody>
		</text>
		<text font="Arial" fontsize="24" fontcolour="#000000" starttime="0" layer="1" xstart="10" ystart="410" xend="110" yend="430">
			<textbody bold="false" italic="false" underlined="true" branch="0">
				<textstring>Morph Costs (Alphabetical) \n</textstring></textbody>
		</text>
		
		<text font="Arial" fontsize="20" fontcolour="#000000" starttime="0" layer="1" xstart="10" ystart="440" xend="40" yend="640">
			<textbody bold="false" italic="false" underlined="false" branch="0">
				<textstring>Type \n</textstring></textbody>
			<textbody bold="false" italic="true" underlined="false" branch="0">
				<textstring>Arachnoid \n Bouncer \n Case \n Dragonfly \n Exalt \n Flat \n Flexbot \n Fury \n Futura \n Ghost \n Hibernoid \n Infomorph \n Menton \n Neo-Avian \n Neo-Hominid \n Neotenic \n Novacrab \n Octomorph \n Olympian \n Pleasure Pod \n Reaper \n Remade \n Ruster \n Slitheroid \n Splicer \n Swarmanoid \n Sylph \n Synth \n Worker Pod \n</textstring></textbody>
		</text>
		<text font="Arial" fontsize="20" fontcolour="#000000" starttime="0" layer="1" xstart="45" ystart="440" xend="75" yend="640">
			<textbody bold="false" italic="false" underlined="false" branch="0">
				<textstring>CP \n</textstring></textbody>
			<textbody bold="false" italic="true" underlined="false" branch="0">
				<textstring>45 \n 40 \n 5 \n 20 \n 30 \n 0 \n 20 \n 75 \n 40 \n 70 \n 25 \n 0 \n 40 \n 25 \n 25 \n 25 \n 60 \n 50 \n 40 \n 20 \n 100 \n 60 \n 25 \n 40 \n 10 \n 25 \n 40 \n 30 \n 20 \n</textstring></textbody>
		</text>
		<text font="Arial" fontsize="20" fontcolour="#000000" starttime="0" layer="1" xstart="80" ystart="440" xend="110" yend="640">
			<textbody bold="false" italic="false" underlined="false" branch="0">
				<textstring>Cost \n</textstring></textbody>
			<textbody bold="false" italic="true" underlined="false" branch="0">
				<textstring>Expensive (40K+) \n Expensive \n Moderate \n High \n Expensive (30K+) \n Expensive (40K+) \n Expensive (50K+) \n Expensive (40K+) \n Expensive \n 0 \n Expensive \n Expensive \n Expensive \n Expensive \n Expensive (30K+) \n Expensive (30K+) \n Expensive \n Expensive \n High \n Expensive \n Expensive \n High \n High \n</textstring></textbody>
		</text>
		<text font="Arial" fontsize="24" fontcolour="#000000" starttime="0" layer="1" xstart="120" ystart="40" xend="230" yend="500">
			<textbody bold="true" italic="false" underlined="true" branch="0">
				<textstring>Backgrounds \n</textstring></textbody>
			<textbody bold="true" italic="false" underlined="false" branch="0">
				<textstring>Drifter: </textstring></textbody>
			<textbody bold="false" italic="true" underlined="false" branch="0">
				<textstring>+10 Navigation Skill, +20 Pilot: \n Spacecraft skill, +10 Networking: \n [Field] skill of your choice \n</textstring></textbody>
			<textbody bold="true" italic="false" underlined="false" branch="0">
				<textstring>Fall Evacuee:</textstring></textbody>
			<textbody bold="false" italic="true" underlined="false" branch="0">
				<textstring>+10 Pilot: Groundcraft \n skill, +10 Networking [Field] skill of \n your choice, +1 Moxie, only 2,500 \n Starting Credit (can still buy credit \n with CP) \n</textstring></textbody>
			<textbody bold="true" italic="false" underlined="false" branch="0">
				<textstring>Hyperelite: </textstring></textbody>
			<textbody bold="false" italic="true" underlined="false" branch="0">
				<textstring>+10 Protocol skill, +10,000 \n Credit, +20 Networking: Hypercorps \n skill, may not start with flat, splicer \n or any pod, uplift or synthetic \n morphs \n</textstring></textbody>
			<textbody bold="true" italic="false" underlined="false" branch="0">
				<textstring>Infolife:</textstring></textbody>
			<textbody bold="false" italic="true" underlined="false" branch="0">
				<textstring>+30 Interfacing skill, \n Computer skills (Infosec, Interfacing, \n Programming, Research) bought \n with Customisation Points are half \n price, Real World Naivete trait, Social \n Stigma (AGI) trait, may not purchase \n Psi trait, Social skill bought with \n Customisation Points are double price \n</textstring></textbody>
			<textbody bold="true" italic="false" underlined="false" branch="0">
				<textstring>Isolate: </textstring></textbody>
			<textbody bold="false" italic="true" underlined="false" branch="0">
				<textstring>+20 to two skills of your choice, \n -10 starting Rep \n</textstring></textbody>
			<textbody bold="true" italic="false" underlined="false" branch="0">
				<textstring>Lost: </textstring></textbody>
			<textbody bold="false" italic="true" underlined="false" branch="0">
				<textstring>+20 to Two Knowledge skills of \n your choice, Psi trait (Level 1), Mental \n Disorder (choose two, this includes the \n one from Psi) trait, Social Stigma (Lost) \n trait, must start with Futura morph \n</textstring></textbody>
			<textbody bold="true" italic="false" underlined="false" branch="0">
				<textstring>Lunar Colonist: </textstring></textbody>
			<textbody bold="false" italic="true" underlined="false" branch="0">
				<textstring>+10 Pilot: Groundcraft \n skill, +10 to one Technical, Academic: \n [Field], or Profession: [Field] skill \n of your choice, +20 Networking: \n Hypercorps skill \n</textstring></textbody>
			<textbody bold="true" italic="false" underlined="false" branch="0">
				<textstring>Martian: </textstring></textbody>
			<textbody bold="false" italic="true" underlined="false" branch="0">
				<textstring>+10 Pilot: Groundcraft skill, \n +10 to one Technical, Academic: \n [Field], or Profession: [Field] skill \n of your choice, +20 Networking: \n Hypercorps skill</textstring></textbody>
			<textbody bold="true" italic="false" underlined="false" branch="0">
				<textstring>Original Space Colonist: </textstring></textbody>
			<textbody bold="false" italic="true" underlined="false" branch="0">
				<textstring>+10 Pilot: \n Spacecraft or Freefall skill, +10 to \n a Technical, Academic: [Field], or \n Profession: [Field] skill of your choice, \n +20 to a Networking: [Field] skill of \n your choice \n</textstring></textbody>
			<textbody bold="true" italic="false" underlined="false" branch="0">
				<textstring>Re-instated:</textstring></textbody>
			<textbody bold="false" italic="true" underlined="false" branch="0">
				<textstring>+10 Pilot: Groundcraft \n skill, +10 to a Networking: [Field] \n skill of your choice, +2 Moxie, Edited \n Memories trait, 0 Starting Credit (can \n still buy credit with CP) \n</textstring></textbody>
			<textbody bold="true" italic="false" underlined="false" branch="0">
				<textstring>Scumborn: </textstring></textbody>
			<textbody bold="false" italic="true" underlined="false" branch="0">
				<textstring>+10 Persuasion or Deception \n skill, +10 Scrounging skill, +20 \n Networking: Autonomists skill \n</textstring></textbody>
			<textbody bold="true" italic="false" underlined="false" branch="0">
				<textstring>Uplift: </textstring></textbody>
			<textbody bold="false" italic="true" underlined="false" branch="0">
				<textstring>+10 Fray skill, +10 Perception skill, \n +20 to two Knowledge skills of your \n choice, must choose an uplift morph \n to start \n</textstring></textbody>
		</text>
		<text font="Arial" fontsize="24" fontcolour="#000000" starttime="0" layer="1" xstart="240" ystart="40" xend="350" yend="500">
			<textbody bold="true" italic="false" underlined="true" branch="0">
				<textstring>Factions\n</textstring></textbody>
			<textbody bold="true" italic="false" underlined="false" branch="0">
				<textstring>Anarchist:</textstring></textbody>
			<textbody bold="false" italic="true" underlined="false" branch="0">
				<textstring>+10 to a skill of your choice, \n +30 Networking: Autonomists skill \n</textstring></textbody>
			<textbody bold="true" italic="false" underlined="false" branch="0">
				<textstring>Argonaut: </textstring></textbody>
			<textbody bold="false" italic="true" underlined="false" branch="0">
				<textstring>+10 to two Technical, \n Academic: [Field] or Profession: \n [Field] skills; +20 Networking: \n Scientists \n</textstring></textbody>
			<textbody bold="true" italic="false" underlined="false" branch="0">
				<textstring>Barsoomian: </textstring></textbody>
			<textbody bold="false" italic="true" underlined="false" branch="0">
				<textstring>+10 Freerunning, +10 \n to one skill of your choice, +20 \n Networking: Autonomists skill \n</textstring></textbody>
			<textbody bold="true" italic="false" underlined="false" branch="0">
				<textstring>Brinker: </textstring></textbody>
			<textbody bold="false" italic="true" underlined="false" branch="0">
				<textstring>+10 Pilot: Spacecraft skill, \n +10 to a skill of your choice, \n +20 to a Networking: [Field] skill of \n your choice \n</textstring></textbody>
			<textbody bold="true" italic="false" underlined="false" branch="0">
				<textstring>Criminal: </textstring></textbody>
			<textbody bold="false" italic="true" underlined="false" branch="0">
				<textstring>+10 Intimidation skill, +30 \n Networking: Criminal skill</textstring></textbody>
			<textbody bold="true" italic="false" underlined="false" branch="0">
				<textstring>Extropian: </textstring></textbody>
			<textbody bold="false" italic="true" underlined="false" branch="0">
				<textstring>+10 Persuasion skill, +20 \n Networking: Autonomists skill, +10 \n Networking: Hypercorps skill \n</textstring></textbody>
			<textbody bold="true" italic="false" underlined="false" branch="0">
				<textstring>Hypercorp: </textstring></textbody>
			<textbody bold="false" italic="true" underlined="false" branch="0">
				<textstring>+10 Protocol skill, +20 \n Networking: Hypercorps skill, +10 to \n any Networking: [Field] skill \n</textstring></textbody>
			<textbody bold="true" italic="false" underlined="false" branch="0">
				<textstring>Jovian: </textstring></textbody>
			<textbody bold="false" italic="true" underlined="false" branch="0">
				<textstring>+10 to two Weapon skills \n of your choice, +10 Fray, +20 \n Networking: Hypercorps skill, must \n start with a Flat or Splicer morph, \n may not start with any nanoware or \n advanced nanotech \n</textstring></textbody>
			<textbody bold="true" italic="false" underlined="false" branch="0">
				<textstring>Lunar: </textstring></textbody>
			<textbody bold="false" italic="true" underlined="false" branch="0">
				<textstring>+10 to one Language: [Field] \n of your choice, +20 Networking: \n Hypercorps skill, +10 Networking: \n Ecologists skill \n</textstring></textbody>
			<textbody bold="true" italic="false" underlined="false" branch="0">
				<textstring>Mercurial: </textstring></textbody>
			<textbody bold="false" italic="true" underlined="false" branch="0">
				<textstring>+10 to any two skills of your \n choice, +20 to a Networking: [Field] \n skill of your choice \n</textstring></textbody>
			<textbody bold="true" italic="false" underlined="false" branch="0">
				<textstring>Scum: </textstring></textbody>
			<textbody bold="false" italic="true" underlined="false" branch="0">
				<textstring>+10 Freefall skill, +10 to a skill \n of your choice, +20 Networking: \n Autonomists skill \n</textstring></textbody>
			<textbody bold="true" italic="false" underlined="false" branch="0">
				<textstring>Socialite: </textstring></textbody>
			<textbody bold="false" italic="true" underlined="false" branch="0">
				<textstring>+10 Persuasion skill, +10 \n Protocol skill, +20 Networking: Media \n skill, may not start with flat, pod, \n uplift or synthetic morphs \n</textstring></textbody>
			<textbody bold="true" italic="false" underlined="false" branch="0">
				<textstring>Titanian: </textstring></textbody>
			<textbody bold="false" italic="true" underlined="false" branch="0">
				<textstring>+10 to two Technical or \n Academic skills of your choice, +20 \n Networking: Autonomists skill \n</textstring></textbody>
			<textbody bold="true" italic="false" underlined="false" branch="0">
				<textstring>Ultimate: </textstring></textbody>
			<textbody bold="false" italic="true" underlined="false" branch="0">
				<textstring>+10 to two skills of your choice, \n +20 to a Networking: [Field] skill of \n your choice, may not start with Flat, \n Splicer, Uplift or Pod morphs \n</textstring></textbody>
			<textbody bold="true" italic="false" underlined="false" branch="0">
				<textstring>Venusian: </textstring></textbody>
			<textbody bold="false" italic="true" underlined="false" branch="0">
				<textstring>+10 Pilot: Aircraft, +10 \n to one skill of your choice, +20 \n Networking: Hypercorps skill \n</textstring></textbody>
		</text>
		<image urlname="src/XMLBits/char1jovian_spy.jpg" xstart="10" ystart="10" width="282" height="463" starttime="0" layer="0" branch="0"></image>

		<shape totalpoints="3" width="100" height="100" fillcolour="#0000FF"
				starttime="1" duration="30" layer="4" linecolour="#FFFFFF" branch="1">
				<point num="00" x="400" y="10"></point>
				<point num="01" x="700" y="40"></point>
				<point num="02" x="650" y="150"></point>
			</shape></slide></slideshow></collection>